examplepy/VERSION
examplepy/__init__.py
examplepy/module1.py
examplepy/tests/__init__.py
examplepy/tests/test_module1.py
example_pypi_package_5782-0.6.0.dist-info/LICENSE
example_pypi_package_5782-0.6.0.dist-info/METADATA
example_pypi_package_5782-0.6.0.dist-info/WHEEL
example_pypi_package_5782-0.6.0.dist-info/top_level.txt
example_pypi_package_5782-0.6.0.dist-info/RECORD
